simple_https/__init__.py
simple_https/simple_https.py
simple_https/src/server.pem
simple_https-0.3.0.dist-info/AUTHORS.rst
simple_https-0.3.0.dist-info/LICENSE
simple_https-0.3.0.dist-info/METADATA
simple_https-0.3.0.dist-info/WHEEL
simple_https-0.3.0.dist-info/entry_points.txt
simple_https-0.3.0.dist-info/top_level.txt
simple_https-0.3.0.dist-info/RECORD
